qurix/__init__.py
qurix/kafka/__init__.py
qurix/kafka/dataframes/__init__.py
qurix/kafka/dataframes/__version__.py
qurix/kafka/dataframes/base_dataframe_convertor.py
qurix/kafka/dataframes/dataframe_consumer.py
qurix/kafka/dataframes/dataframe_convertor.py
qurix/kafka/dataframes/dataframe_producer.py
qurix/kafka/dataframes/header.py
qurix/kafka/dataframes/message_formats.py
tests/__init__.py
tests/common.py
tests/test_dataframe_consumer.py
tests/test_dataframe_convertor.py
tests/test_dataframe_producer.py
qurix_kafka_dataframes-1.3.1.dist-info/METADATA
qurix_kafka_dataframes-1.3.1.dist-info/WHEEL
qurix_kafka_dataframes-1.3.1.dist-info/top_level.txt
qurix_kafka_dataframes-1.3.1.dist-info/RECORD
